Workbook

Sheet SUM
B3: * 2018 8월 선적계획및 당월선적 입금계획(OA 적용)_7월이월포함 | G3: 6월 전월이월 | K3: 43313 | L3: 43313 | M3: 43313 | N3: 43313 | O3: 43313 | P3: 43313 | Q3: 43313 | R3: 43313 | S3: 43313 | T3: 43313 | U3: 43313 | V3: 43313 | W3: 43313 | X3: 43313
B4: 내 역 | C4: BVT 선적계획 | D4: ETP 선적계획 | E4: 합 계 | H4: 6월 선적금액 | I4: 입금및 선수금.내수 | J4: 잔 액
B5: 8월 선적예정 | C5: ='BVT 선적계획'!L7 -> 0 | D5: =IFERROR('ETP 선적계획'!L7,0) -> 0 | E5: =C5+D5 -> 0 | G5: 4.5월선적미수금 | J5: 393557.46
B6: 8월 선적금액 | C6: ='BVT 선적계획'!M7 -> 0 | D6: =IFERROR('ETP 선적계획'!M7,0) -> 0 | E6: =C6+D6 -> 0 | G6: 6월선적 | H6: 10730179 | I6: 5724683.5 | J6: 5005495.3
B7: 잔 액 예 정 | C7: =C5-C6 -> 0 | D7: =D5-D6 -> 0 | E7: =C7+D7 -> 0 | G7: 7월로이월 | H7: 341408.33
B8: 내 역 | C8: 당월입금계획 | D8: OA예정 | E8: 합 계
B9: 8월 입금계획 | C9: ='BVT 선적계획'!W7+'BVT 선적계획'!X7 -> 0 | E9: =SUM(C9:D9) -> 0 | H9: 11071587 | I9: 5724683.5 | J9: 5399052.7
B10: 입금금액 | C10: =-F19 -> 0 | E10: =SUM(C10:D10) -> 0
B11: G.TOTAL | C11: =SUM(C9:C10) -> 0 | D11: =SUM(D9:D10) -> 0 | E11: =SUM(E9:E10) -> 0
B13: * 2018 8월 입금 계획
B14: 8월 선적계획 | C14: 내 역 | D14: 8월선적 입금계획 | Y14: G.TOTAL
D15: 당사수입.선수금 | E15: BVT CM Order | F15: 10일전 | G15: 1 | H15: 2 | I15: 3 | J15: 4 | K15: 5 | L15: 6 | M15: 7 | N15: 8 | O15: 9 | P15: 10 | Q15: 11 | R15: 12 | S15: 1 | T15: 2 | U15: 3 | V15: 4 | W15: 5 | X15: 6
B16: =C5 -> 0 | C16: BVT당월선적 입금예정_OA포함 | D16: ='BVT 선적계획'!U7 -> 0 | E16: ='BVT 선적계획'!V7 -> 0 | F16: ='BVT 선적계획'!W7 -> 0 | G16: ='BVT 선적계획'!X7 -> 0 | H16: ='BVT 선적계획'!Y7 -> 0 | I16: ='BVT 선적계획'!Z7 -> 0 | J16: ='BVT 선적계획'!AA7 -> 0 | K16: ='BVT 선적계획'!AB7 -> 0 | ... X16: ='BVT 선적계획'!AO7 -> 0 | Y16: =SUM(D16:X16) -> 0
B17: =D5 -> 0 | C17: ETP당월 선적 입금계획 | D17: =IFERROR('ETP 선적계획'!U7,0) -> 0 | E17: =IFERROR('ETP 선적계획'!V7,0) -> 0 | F17: =IFERROR('ETP 선적계획'!W7,0) -> 0 | G17: =IFERROR('ETP 선적계획'!X7,0) -> 0 | H17: =IFERROR('ETP 선적계획'!Y7,0) -> 0 | I17: =IFERROR('ETP 선적계획'!Z7,0) -> 0 | J17: =IFERROR('ETP 선적계획'!AA7,0) -> 0 | K17: =IFERROR('ETP 선적계획'!AB7,0) -> 0 | ... X17: =IFERROR('ETP 선적계획'!AO7,0) -> 0 | Y17: =SUM(D17:X17) -> 0
B18: 4.5.6.7월출고미수금 | C18: 전월이월 외상매출금 | D18: 재경팀자료 | Y18: =SUM(D18:X18) -> 0
C19: 입 금 완 료 | Y19: =SUM(D19:X19) -> 0
B20: OA 입금예정 | Y20: =SUM(D20:X20) -> 0
B21: 입금 예정 G.TOTAL | D21: =SUM(D16:D20) -> 0 | E21: =SUM(E16:E20) -> 0 | F21: =SUM(F16:F20) -> 0 | G21: =SUM(G16:G20) -> 0 | H21: =SUM(H16:H20) -> 0 | I21: =SUM(I16:I20) -> 0 | J21: =SUM(J16:J20) -> 0 | K21: =SUM(K16:K20) -> 0 | ... X21: =SUM(X16:X20) -> 0 | Y21: =SUM(D21:X21) -> 0
C57: * 출고계획 | D57: BVT | P57: ETP
C58: BUYER | D58: 1 | E58: 2 | F58: 3 | G58: 4 | H58: 5 | I58: 6 | J58: 7 | K58: 8 | L58: 9 | M58: 10 | N58: 11 | O58: 12 | P58: 1 | Q58: 2 | R58: 3 | S58: 4 | T58: 5 | U58: 6 | V58: 7 | W58: 8 | X58: 9 | Y58: 10 | Z58: 11 | AA58: 12
C59: TOTAL | D59: =SUM(D60:D62) -> 0 | E59: =SUM(E60:E62) -> 0 | F59: =SUM(F60:F62) -> 0 | G59: =SUM(G60:G62) -> 0 | H59: =SUM(H60:H62) -> 0 | I59: =SUM(I60:I62) -> 0 | J59: =SUM(J60:J62) -> 0 | K59: =SUM(K60:K62) -> 0 | ... V59: =SUM(V60:V62) -> 0 | Y59: =SUM(Y60:Y62) -> 0 | Z59: =SUM(Z60:Z62) -> 0 | AA59: =SUM(AA60:AA62) -> 0

Sheet BVT 선적계획
B2: Buyer | C2: Month | D2: PoNo | E2: OrderNo | F2: Style Name | G2: Order Quantity | H2: Plan Shipping Quantity | I2: shipped qty | J2: Balance q'ty | K2: Price | L2: Total Sales | M2: shipped amount | N2: Balance AMT | O2: Possible Date | P2: Invoice No | Q2: OnBoard Date | R2: 비 고 | S2: 계약서(PI) | T2: 당월 출고 입금계획 | W2: 당월 출고 입금계획
U3: 선수금 | V3: BVT | W3: 10일 이전 | X3: 1 | Y3: 2 | Z3: 3 | AA3: 4 | AB3: 5 | AC3: 6 | AD3: 7 | AE3: 8 | AF3: 9 | AG3: 10 | AH3: 11 | AI3: 12 | AJ3: 1 | AK3: 2 | AL3: 3 | AM3: 4 | AN3: 5 | AO3: 6 | AP3: 비 고
H7: =SUM(H4:H6) -> 0 | L7: =SUM(L4:L6) -> 0 | M7: =SUM(M4:M6) -> 0 | U7: =SUM(U4:U6) -> 0 | V7: =SUM(V4:V6) -> 0 | W7: =SUM(W4:W6) -> 0 | X7: =SUM(X4:X6) -> 0 | Y7: =SUM(Y4:Y6) -> 0 | Z7: =SUM(Z4:Z6) -> 0 | AA7: =SUM(AA4:AA6) -> 0 | AB7: =SUM(AB4:AB6) -> 0 | ... AP7: =SUM(AP4:AP6) -> 0
U8: =SUM(U7:AP7) -> 0
F10: * 출고계획 | G10: BVT
F11: BUYER | G11: 출고예정금액 | H11: 실적 | I11: Balance Amt | J11: Balance Qty | K11: 비 고
F15: TOTAL | G15: =SUM(G12:G14) -> 0 | H15: =SUM(H12:H14) -> 0 | I15: =SUM(I12:I14) -> 0 | J15: =SUM(J12:J14) -> 0

Sheet ETP 선적계획
B2: Buyer | C2: Month | D2: PoNo | E2: OrderNo | F2: Style Name | G2: Order Quantity | H2: Plan Shipping Quantity | I2: shipped qty | J2: Balance q'ty | K2: Price | L2: Total Sales | M2: shipped amount | N2: Balance AMT | O2: Possible Date | P2: Invoice No | Q2: OnBoard Date | R2: 비 고 | S2: 계약서(PI) | T2: 당월 출고 입금계획 | W2: 당월 출고 입금계획
U3: 선수금 | V3: ETP | W3: 10일 이전 | X3: 1 | Y3: 2 | Z3: 3 | AA3: 4 | AB3: 5 | AC3: 6 | AD3: 7 | AE3: 8 | AF3: 9 | AG3: 10 | AH3: 11 | AI3: 12 | AJ3: 1 | AK3: 2 | AL3: 3 | AM3: 4 | AN3: 5 | AO3: 6 | AP3: 비 고
H7: =SUM(H4:H6) -> 0 | L7: =SUM(L4:L6) -> 0 | M7: =SUM(M4:M6) -> 0 | U7: =SUM(U4:U6) -> 0 | V7: =SUM(V4:V6) -> 0 | W7: =SUM(W4:W6) -> 0 | X7: =SUM(X4:X6) -> 0 | Y7: =SUM(Y4:Y6) -> 0 | Z7: =SUM(Z4:Z6) -> 0 | AA7: =SUM(AA4:AA6) -> 0 | AB7: =SUM(AB4:AB6) -> 0 | ... AP7: =SUM(AP4:AP6) -> 0
U8: =SUM(U7:AP7) -> 0
F10: * 출고계획 | G10: ETP
F11: BUYER | G11: 출고예정금액 | H11: 실적 | I11: Balance Amt | J11: Balance Qty | K11: 비 고
F15: TOTAL | G15: =SUM(G12:G14) -> 0 | H15: =SUM(H12:H14) -> 0 | I15: =SUM(I12:I14) -> 0 | J15: =SUM(J12:J14) -> 0
