Workbook

Sheet SUM
B3: * 2018 8월 선적계획및 당월선적 입금계획(OA 적용)_7월이월포함 | G3: 6월 전월이월 | K3: 43313
B4: 내 역 | C4: BVT 선적계획 | D4: ETP 선적계획 | E4: 합 계 | H4: 6월 선적금액 | I4: 입금및 선수금.내수 | J4: 잔 액
B5: 8월 선적예정 | C5: ='BVT 선적계획'!L7 -> 0 | D5: ='ETP 선적계획'!L7 -> 0 | E5: =C5+D5 -> 0 | G5: 4.5월선적미수금 | J5: 393557.46
B6: 8월 선적금액 | C6: ='BVT 선적계획'!M7 -> 0 | D6: ='ETP 선적계획'!M7 -> 0 | E6: =C6+D6 -> 0 | G6: 6월선적 | H6: 10730179 | I6: 5724683.5 | J6: 5005495.3
B7: 전월이월금액 | E7: =C7+D7 -> 0 | G7: 7월로이월 | H7: 341408.33
B8: G.TOTAL | C8: =C5-C6 -> 0 | D8: =D5-D6 -> 0 | E8: =SUM(E6:E7) -> 0
H9: 11071587 | I9: 5724683.5 | J9: 5399052.7
B11: 내 역 | C11: 당월입금계획 | D11: 전월입금계획 | E11: 합 계
B12: 8월 입금계획 | C12: =('BVT 선적계획'!W7+'BVT 선적계획'!X7) + ('ETP 선적계획'!W7+'ETP 선적계획'!X7) -> 0 | E12: =SUM(C12:D12) -> 0
B13: 입금금액 | C13: =-F23 -> 0 | E13: =SUM(C13:D13) -> 0
B14: G.TOTAL | C14: =SUM(C12:C13) -> 0 | D14: =SUM(D12:D13) -> 0 | E14: =SUM(E12:E13) -> 0
L16: 2018.08.03 기준 | N16: =#REF!-533000 -> #REF!
B17: * 2018 8월 입금 계획 | L17: 2018.08.03 기준 | N17: =#REF!-533000 -> #REF!
B18: 8월 선적계획 | C18: 내 역 | D18: 8월선적 입금계획 | L18: G.TOTAL
D19: 당사수입.선수금 | E19: BVT CM Order | F19: 8/1-8월8일전 | H19: 9월입금 | I19: 10월입금 | J19: 11월입금 | K19: 12월입금 | N19: OA | O19: 7 | P19: 8 | Q19: 9
B20: =C5 -> 0 | C20: BVT당월선적 입금계획 | D20: ='BVT 선적계획'!U7 -> 0 | E20: ='BVT 선적계획'!V7 -> 0 | F20: ='BVT 선적계획'!W7 -> 0 | G20: ='BVT 선적계획'!X7 -> 0 | H20: ='BVT 선적계획'!Y7 -> 0 | I20: ='BVT 선적계획'!Z7 -> 0 | J20: ='BVT 선적계획'!AA7 -> 0 | K20: ='BVT 선적계획'!AB7 -> 0 | L20: =SUM(D20:K20) -> 0 | N20: DN | O20: 586414 | P20: 412657
B21: =D5 -> 0 | C21: ETP당월 선적 입금계획 | D21: ='ETP 선적계획'!U7 -> 0 | E21: ='ETP 선적계획'!V7 -> 0 | F21: ='ETP 선적계획'!W7 -> 0 | G21: ='ETP 선적계획'!X7 -> 0 | H21: ='ETP 선적계획'!Y7 -> 0 | I21: ='ETP 선적계획'!Z7 -> 0 | J21: ='ETP 선적계획'!AA7 -> 0 | K21: ='ETP 선적계획'!AB7 -> 0 | L21: =SUM(D21:K21) -> 0 | N21: OL | O21: 14609 | P21: 672000 | Q21: 819656
C22: 전월이월 외상매출금 | D22: 재경팀자료 | L22: =SUM(D22:K22) -> 0
C23: 입 금 완 료 | L23: =SUM(D23:K23) -> 0 | N23: TR | P23: =SUM('BVT 선적계획'!#REF!) -> #REF! | Q23: =SUM('BVT 선적계획'!#REF!) -> #REF!
L24: =SUM(D24:K24) -> 0 | N24: OA | O24: 7 | P24: 8 | Q24: 9
B25: 입금 예정 G.TOTAL | D25: =SUM(D20:D24) -> 0 | E25: =SUM(E20:E24) -> 0 | F25: =SUM(F20:F24) -> 0 | G25: =SUM(G20:G24) -> 0 | H25: =SUM(H20:H24) -> 0 | I25: =SUM(I20:I24) -> 0 | J25: =SUM(J20:J24) -> 0 | K25: =SUM(K20:K24) -> 0 | L25: =SUM(D25:K25) -> 0 | N25: DN
C61: * 출고계획 | D61: BVT | H61: ETP
C62: BUYER | D62: 출고예정금액 | E62: 실적 | F62: Balance Amt | G62: Balance Qty | H62: 출고예정금액 | I62: 실적 | J62: Balance Amt | K62: Balance Qty | L62: 비 고
C66: TOTAL | D66: =SUM(D63:D65) -> 0 | E66: =SUM(E63:E65) -> 0 | F66: =SUM(F63:F65) -> 0 | G66: =SUM(G63:G65) -> 0 | H66: =SUM(H63:H65) -> 0 | I66: =SUM(I63:I65) -> 0 | J66: =SUM(J63:J65) -> 0 | K66: =SUM(K63:K65) -> 0

Sheet BVT 선적계획
B2: Buyer | C2: Month | D2: PoNo | E2: OrderNo | F2: Style Name | G2: Order Quantity | H2: Plan Shipping Quantity | I2: shipped qty | J2: Balance q'ty | K2: Price | L2: Total Sales | M2: shipped amount | N2: Balance AMT | O2: Possible Date | P2: Invoice No | Q2: OnBoard Date | R2: 비 고 | S2: 계약서(PI) | T2: 당월 출고 입금계획 | W2: 당월 출고 입금계획
U3: 선수금 | V3: BVT | W3: 10일 이전 | X3: 8월 | Y3: 9월 | Z3: 10 | AA3: 11 | AB3: 비 고
H7: =SUM(H4:H6) -> 0 | L7: =SUM(L4:L6) -> 0 | M7: =SUM(M4:M6) -> 0 | U7: =SUM(U4:U6) -> 0 | V7: =SUM(V4:V6) -> 0 | W7: =SUM(W4:W6) -> 0 | X7: =SUM(X4:X6) -> 0 | Y7: =SUM(Y4:Y6) -> 0 | Z7: =SUM(Z4:Z6) -> 0 | AA7: =SUM(AA4:AA6) -> 0 | AB7: =SUM(AB4:AB6) -> 0
U8: =SUM(U7:AB7) -> 0
F10: * 출고계획 | G10: BVT
F11: BUYER | G11: 출고예정금액 | H11: 실적 | I11: Balance Amt | J11: Balance Qty | K11: 비 고
F15: TOTAL | G15: =SUM(G12:G14) -> 0 | H15: =SUM(H12:H14) -> 0 | I15: =SUM(I12:I14) -> 0 | J15: =SUM(J12:J14) -> 0

Sheet ETP 선적계획
B2: Buyer | C2: Month | D2: PoNo | E2: OrderNo | F2: Style Name | G2: Order Quantity | H2: Plan Shipping Quantity | I2: shipped qty | J2: Balance q'ty | K2: Price | L2: Total Sales | M2: shipped amount | N2: Balance AMT | O2: Possible Date | P2: Invoice No | Q2: OnBoard Date | R2: 비 고 | S2: 계약서(PI) | T2: 당월 출고 입금계획 | W2: 당월 출고 입금계획
U3: 선수금 | V3: BVT | W3: 10일 이전 | X3: 8월 | Y3: 9월 | Z3: 10 | AA3: 11 | AB3: 비 고
H7: =SUM(H4:H6) -> 0 | L7: =SUM(L4:L6) -> 0 | M7: =SUM(M4:M6) -> 0 | U7: =SUM(U4:U6) -> 0 | V7: =SUM(V4:V6) -> 0 | W7: =SUM(W4:W6) -> 0 | X7: =SUM(X4:X6) -> 0 | Y7: =SUM(Y4:Y6) -> 0 | Z7: =SUM(Z4:Z6) -> 0 | AA7: =SUM(AA4:AA6) -> 0 | AB7: =SUM(AB4:AB6) -> 0
U8: =SUM(U7:AB7) -> 0
F10: * 출고계획 | G10: ETP
F11: BUYER | G11: 출고예정금액 | H11: 실적 | I11: Balance Amt | J11: Balance Qty | K11: 비 고
F15: TOTAL | G15: =SUM(G12:G14) -> 0 | H15: =SUM(H12:H14) -> 0 | I15: =SUM(I12:I14) -> 0 | J15: =SUM(J12:J14) -> 0
