Workbook

Sheet I
A1: PROFORMA INVOICE FOR SHINTS
A3: No | B3: HS_No | C3: Matl Name | D3: Unit Price | E3: Q'ty | F3: Unit | G3: Amount | H3: Country | I3: Weight | K3: Width | L3: Composition
J4: kg
J5: kg
B6: GRAND TOTAL : | E6: =SUM(E4:E5) -> 0 | G6: =SUM(G4:G5) -> 0 | I6: =SUM(I4:I5) -> 0 | J6: kg

Sheet SHINTS
A1: COMMERCIAL INVOICE
A2: 1) Shipper/ Exporter : | G2: 8) No & Date of Invoice
A3: SHIN TEXTILE SOLUTIONS CO., LTD.
A4: 801, E&C VENTURE DREAMTOWER 2 | G4: STS-S11-026 | K4: 40711
A5: 55, DIGITAL-RO 33-GIL, GURO-GU, SEOUL, KOREA | G5: 9) No & Date L/C
A6: TEL : 070-4659-3337 FAX : 82-2-6330-2019
A7: 2) Consignee :
A8: SHINTS BVT CO.,LTD VAT:0800006025 | G8: 10) L/C issuing bank
A9: PHU TAO RESIDENTIAL AREA,THACH KHOI WARD
A10: HAI DUONG CITY,HAI DUONG PROVINCE - VIETNAM
A11: TEL:84-320-3861727 FAX:84-320-3861730 | G11: 11) Remarks:
A12: XNK-Thy Ha <thyha@shintsbvt.com>
A13: 3) Notify party : | I13: FREIGHT CHARGE : | J13: =1500/324106.53*J29 -> 0
A14: THE SAME AS ABOVE | I14: INSURANCE CHARGE : | J14: =J29*1.1*0.026% -> 0
I15: 제조자 미상
A16: 4) Port of loading: | D16: 5) Final Destination: | H16: C/T : | I16: 0 | J16: CT
H17: NET : | I17: =I!I6 -> 0 | J17: KGS
A18: INCHEON, KOREA | D18: HAIPHONG, VIETNAM | H18: GRS : | I18: =I17*1.1 -> 0 | J18: KGS
A19: 6) Carrier | D19: 7) Sailing on/ or About
A22: 12) Marks and Number of PKGS | D22: 13) Description of Goods | G22: 14) Quantity/Uint | I22: 15) Unit/price | J22: 16) Amount
G24: ( CIF HAIPHONG, VIETNAM )
D29: TOTAL | J29: =I!G6 -> 0
A42: TEL NO. : 070-4006-3700~14, (DIR. 070-4006-3727)
A43: FAX NO. : (02)6330-2019 | H43: 17).Signed by :

Sheet V1
A1: COMMERCIAL INVOICE
A2: 1) Shipper/ Exporter : | G2: 8) No & Date of Invoice
A3: SHIN TEXTILE SOLUTIONS CO., LTD.
A4: 801, E&C VENTURE DREAMTOWER 2
A5: 55, DIGITAL-RO 33-GIL, GURO-GU, SEOUL, KOREA | G5: 9) No & Date L/C
A6: TEL : 070-4659-3337 FAX : 82-2-6330-2019
A7: 2) Consignee :
A8: SHINTS BVT CO.,LTD VAT:0800006025 | G8: 10) L/C issuing bank
A9: PHU TAO RESIDENTIAL AREA,THACH KHOI WARD
A10: HAI DUONG CITY,HAI DUONG PROVINCE - VIETNAM
A11: TEL:84-320-3861727 FAX:84-320-3861730 | G11: 11) Remarks:
A12: XNK-Thy Ha <thyha@shintsbvt.com>
A13: 3) Notify party : | I13: FREIGHT CHARGE : | J13: =1500/324106.53*J61 -> 0
A14: THE SAME AS ABOVE | I14: INSURANCE CHARGE : | J14: =J61*1.1*0.026% -> 0
A16: 4) Port of loading: | D16: 5) Final Destination: | H16: C/T : | I16: - | J16: CT
H17: NET : | I17: =K61 -> 0 | J17: KGS
A18: INCHEON, KOREA | D18: HAIPHONG, VIETNAM | H18: GRS : | I18: =I17*1.1 -> 0 | J18: KGS
A19: 6) Carrier | D19: 7) Sailing on/ or About
A22: 12) Marks and Number of PKGS | D22: 13) Description of Goods | G22: 14) Quantity/Uint | I22: 15) Unit/price | J22: 16) Amount
G24: ( CIF HAIPHONG, VIETNAM )
D26: Desc | G26: Q'ty | H26: Unit | I26: Price | J26: Total
J27: =G27*I27 -> 0
J28: =G28*I28 -> 0
J29: =G29*I29 -> 0
J30: =G30*I30 -> 0
J31: =G31*I31 -> 0
J32: =G32*I32 -> 0
J33: =G33*I33 -> 0
J34: =G34*I34 -> 0
J35: =G35*I35 -> 0
J36: =G36*I36 -> 0
J37: =G37*I37 -> 0
J38: =G38*I38 -> 0
... J60: =G60*I60 -> 0
D61: TOTAL | J61: =SUM(J27:J60) -> 0 | K61: 0
A62: DESC/SPEC | D62: HS CODE | F62: OFFER SPEC
A102: TEL NO. : 070-4006-3700~14, (DIR. 070-4006-3727)
A103: FAX NO. : (02)6330-2019 | H103: 17).Signed by :

Sheet V2
A1: COMMERCIAL INVOICE
A2: 1) Shipper/ Exporter : | G2: 8) No & Date of Invoice
A3: SHIN TEXTILE SOLUTIONS CO., LTD.
A4: 801, E&C VENTURE DREAMTOWER 2
A5: 55, DIGITAL-RO 33-GIL, GURO-GU, SEOUL, KOREA | G5: 9) No & Date L/C
A6: TEL : 070-4659-3337 FAX : 82-2-6330-2019
A7: 2) Consignee :
A8: SHINTS BVT CO.,LTD VAT:0800006025 | G8: 10) L/C issuing bank
A9: PHU TAO RESIDENTIAL AREA,THACH KHOI WARD
A10: HAI DUONG CITY,HAI DUONG PROVINCE - VIETNAM
A11: TEL:84-320-3861727 FAX:84-320-3861730 | G11: 11) Remarks:
A12: XNK-Thy Ha <thyha@shintsbvt.com>
A13: 3) Notify party : | I13: FREIGHT CHARGE : | J13: =1500/324106.53*J61 -> 0
A14: THE SAME AS ABOVE | I14: INSURANCE CHARGE : | J14: =J61*1.1*0.026% -> 0
A16: 4) Port of loading: | D16: 5) Final Destination: | H16: C/T : | I16: - | J16: CT
H17: NET : | I17: =K61 -> 0 | J17: KGS
A18: INCHEON, KOREA | D18: HAIPHONG, VIETNAM | H18: GRS : | I18: =I17*1.1 -> 0 | J18: KGS
A19: 6) Carrier | D19: 7) Sailing on/ or About
A22: 12) Marks and Number of PKGS | D22: 13) Description of Goods | G22: 14) Quantity/Uint | I22: 15) Unit/price | J22: 16) Amount
G24: ( CIF HAIPHONG, VIETNAM )
D26: Desc | G26: Q'ty | H26: Unit | I26: Price | J26: Total
J27: =G27*I27 -> 0
J28: =G28*I28 -> 0
J29: =G29*I29 -> 0
J30: =G30*I30 -> 0
J31: =G31*I31 -> 0
J32: =G32*I32 -> 0
J33: =G33*I33 -> 0
J34: =G34*I34 -> 0
J35: =G35*I35 -> 0
J36: =G36*I36 -> 0
J37: =G37*I37 -> 0
J38: =G38*I38 -> 0
... J60: =G60*I60 -> 0
D61: TOTAL | J61: =SUM(J27:J60) -> 0 | K61: 0
A62: DESC/SPEC | D62: HS CODE | F62: OFFER SPEC
A102: TEL NO. : 070-4006-3700~14, (DIR. 070-4006-3727)
A103: FAX NO. : (02)6330-2019 | H103: 17).Signed by :

Sheet V3
A1: COMMERCIAL INVOICE
A2: 1) Shipper/ Exporter : | G2: 8) No & Date of Invoice
A3: SHIN TEXTILE SOLUTIONS CO., LTD.
A4: 801, E&C VENTURE DREAMTOWER 2
A5: 55, DIGITAL-RO 33-GIL, GURO-GU, SEOUL, KOREA | G5: 9) No & Date L/C
A6: TEL : 070-4659-3337 FAX : 82-2-6330-2019
A7: 2) Consignee :
A8: SHINTS BVT CO.,LTD VAT:0800006025 | G8: 10) L/C issuing bank
A9: PHU TAO RESIDENTIAL AREA,THACH KHOI WARD
A10: HAI DUONG CITY,HAI DUONG PROVINCE - VIETNAM
A11: TEL:84-320-3861727 FAX:84-320-3861730 | G11: 11) Remarks:
A12: XNK-Thy Ha <thyha@shintsbvt.com>
A13: 3) Notify party : | I13: FREIGHT CHARGE : | J13: =1500/324106.53*J29 -> 0
A14: THE SAME AS ABOVE | I14: INSURANCE CHARGE : | J14: =J29*1.1*0.026% -> 0
A16: 4) Port of loading: | D16: 5) Final Destination: | H16: C/T : | I16: 0 | J16: CT
H17: NET : | I17: =K29 -> 0 | J17: KGS
A18: INCHEON, KOREA | D18: HAIPHONG, VIETNAM | H18: GRS : | I18: =I17*1.1 -> 0 | J18: KGS
A19: 6) Carrier | D19: 7) Sailing on/ or About
A22: 12) Marks and Number of PKGS | D22: 13) Description of Goods | G22: 14) Quantity/Uint | I22: 15) Unit/price | J22: 16) Amount
G24: ( CIF HAIPHONG, VIETNAM )
D26: Desc | G26: Q'ty | H26: Unit | I26: Price | J26: Total
J27: =G27*I27 -> 0
J28: =G28*I28 -> 0
D29: TOTAL | J29: =SUM(J27:J28) -> 0 | K29: =SUM(K27:K28) -> 0
A30: DESC/SPEC | D30: HS CODE | F30: OFFER SPEC
A37: TEL NO. : 070-4006-3700~14, (DIR. 070-4006-3727)
A38: FAX NO. : (02)6330-2019 | H38: 17).Signed by :

Sheet V4
A1: COMMERCIAL INVOICE
A2: 1) Shipper/ Exporter : | G2: 8) No & Date of Invoice
A3: SHIN TEXTILE SOLUTIONS CO., LTD.
A4: 801, E&C VENTURE DREAMTOWER 2
A5: 55, DIGITAL-RO 33-GIL, GURO-GU, SEOUL, KOREA | G5: 9) No & Date L/C
A6: TEL : 070-4659-3337 FAX : 82-2-6330-2019
A7: 2) Consignee :
A8: SHINTS BVT CO.,LTD VAT:0800006025 | G8: 10) L/C issuing bank
A9: PHU TAO RESIDENTIAL AREA,THACH KHOI WARD
A10: HAI DUONG CITY,HAI DUONG PROVINCE - VIETNAM
A11: TEL:84-320-3861727 FAX:84-320-3861730 | G11: 11) Remarks:
A12: XNK-Thy Ha <thyha@shintsbvt.com>
A13: 3) Notify party : | I13: FREIGHT CHARGE : | J13: =1500/324106.53*J29 -> 0
A14: THE SAME AS ABOVE | I14: INSURANCE CHARGE : | J14: =J29*1.1*0.026% -> 0
A16: 4) Port of loading: | D16: 5) Final Destination: | H16: C/T : | I16: 0 | J16: CT
H17: NET : | I17: =K29 -> 0 | J17: KGS
A18: INCHEON, KOREA | D18: HAIPHONG, VIETNAM | H18: GRS : | I18: =I17*1.1 -> 0 | J18: KGS
A19: 6) Carrier | D19: 7) Sailing on/ or About
A22: 12) Marks and Number of PKGS | D22: 13) Description of Goods | G22: 14) Quantity/Uint | I22: 15) Unit/price | J22: 16) Amount
G24: ( CIF HAIPHONG, VIETNAM )
D26: Desc | G26: Q'ty | H26: Unit | I26: Price | J26: Total
J27: =G27*I27 -> 0
J28: =G28*I28 -> 0
D29: TOTAL | J29: =SUM(J27:J28) -> 0 | K29: =SUM(K27:K28) -> 0
A30: DESC/SPEC | D30: HS CODE | F30: OFFER SPEC
A37: TEL NO. : 070-4006-3700~14, (DIR. 070-4006-3727)
A38: FAX NO. : (02)6330-2019 | H38: 17).Signed by :

Sheet V5
A1: COMMERCIAL INVOICE
A2: 1) Shipper/ Exporter : | G2: 8) No & Date of Invoice
A3: SHIN TEXTILE SOLUTIONS CO., LTD.
A4: 801, E&C VENTURE DREAMTOWER 2
A5: 55, DIGITAL-RO 33-GIL, GURO-GU, SEOUL, KOREA | G5: 9) No & Date L/C
A6: TEL : 070-4659-3337 FAX : 82-2-6330-2019
A7: 2) Consignee :
A8: SHINTS BVT CO.,LTD VAT:0800006025 | G8: 10) L/C issuing bank
A9: PHU TAO RESIDENTIAL AREA,THACH KHOI WARD
A10: HAI DUONG CITY,HAI DUONG PROVINCE - VIETNAM
A11: TEL:84-320-3861727 FAX:84-320-3861730 | G11: 11) Remarks:
A12: XNK-Thy Ha <thyha@shintsbvt.com>
A13: 3) Notify party : | I13: FREIGHT CHARGE : | J13: =1500/324106.53*J29 -> 0
A14: THE SAME AS ABOVE | I14: INSURANCE CHARGE : | J14: =J29*1.1*0.026% -> 0
A16: 4) Port of loading: | D16: 5) Final Destination: | H16: C/T : | I16: 0 | J16: CT
H17: NET : | I17: =K29 -> 0 | J17: KGS
A18: INCHEON, KOREA | D18: HAIPHONG, VIETNAM | H18: GRS : | I18: =I17*1.1 -> 0 | J18: KGS
A19: 6) Carrier | D19: 7) Sailing on/ or About
A22: 12) Marks and Number of PKGS | D22: 13) Description of Goods | G22: 14) Quantity/Uint | I22: 15) Unit/price | J22: 16) Amount
G24: ( CIF HAIPHONG, VIETNAM )
D26: Desc | G26: Q'ty | H26: Unit | I26: Price | J26: Total
J27: =G27*I27 -> 0
J28: =G28*I28 -> 0
D29: TOTAL | J29: =SUM(J27:J28) -> 0 | K29: =SUM(K27:K28) -> 0
A30: DESC/SPEC | D30: HS CODE | F30: OFFER SPEC
A37: TEL NO. : 070-4006-3700~14, (DIR. 070-4006-3727)
A38: FAX NO. : (02)6330-2019 | H38: 17).Signed by :

Sheet V6
A1: COMMERCIAL INVOICE
A2: 1) Shipper/ Exporter : | G2: 8) No & Date of Invoice
A3: SHIN TEXTILE SOLUTIONS CO., LTD.
A4: 801, E&C VENTURE DREAMTOWER 2
A5: 55, DIGITAL-RO 33-GIL, GURO-GU, SEOUL, KOREA | G5: 9) No & Date L/C
A6: TEL : 070-4659-3337 FAX : 82-2-6330-2019
A7: 2) Consignee :
A8: SHINTS BVT CO.,LTD VAT:0800006025 | G8: 10) L/C issuing bank
A9: PHU TAO RESIDENTIAL AREA,THACH KHOI WARD
A10: HAI DUONG CITY,HAI DUONG PROVINCE - VIETNAM
A11: TEL:84-320-3861727 FAX:84-320-3861730 | G11: 11) Remarks:
A12: XNK-Thy Ha <thyha@shintsbvt.com>
A13: 3) Notify party : | I13: FREIGHT CHARGE : | J13: =1500/324106.53*J29 -> 0
A14: THE SAME AS ABOVE | I14: INSURANCE CHARGE : | J14: =J29*1.1*0.026% -> 0
A16: 4) Port of loading: | D16: 5) Final Destination: | H16: C/T : | I16: 0 | J16: CT
H17: NET : | I17: =K29 -> 0 | J17: KGS
A18: INCHEON, KOREA | D18: HAIPHONG, VIETNAM | H18: GRS : | I18: =I17*1.1 -> 0 | J18: KGS
A19: 6) Carrier | D19: 7) Sailing on/ or About
A22: 12) Marks and Number of PKGS | D22: 13) Description of Goods | G22: 14) Quantity/Uint | I22: 15) Unit/price | J22: 16) Amount
G24: ( CIF HAIPHONG, VIETNAM )
D26: Desc | G26: Q'ty | H26: Unit | I26: Price | J26: Total
J27: =G27*I27 -> 0
J28: =G28*I28 -> 0
D29: TOTAL | J29: =SUM(J27:J28) -> 0 | K29: =SUM(K27:K28) -> 0
A30: DESC/SPEC | D30: HS CODE | F30: OFFER SPEC
A37: TEL NO. : 070-4006-3700~14, (DIR. 070-4006-3727)
A38: FAX NO. : (02)6330-2019 | H38: 17).Signed by :

Sheet V7
A1: COMMERCIAL INVOICE
A2: 1) Shipper/ Exporter : | G2: 8) No & Date of Invoice
A3: SHIN TEXTILE SOLUTIONS CO., LTD.
A4: 801, E&C VENTURE DREAMTOWER 2
A5: 55, DIGITAL-RO 33-GIL, GURO-GU, SEOUL, KOREA | G5: 9) No & Date L/C
A6: TEL : 070-4659-3337 FAX : 82-2-6330-2019
A7: 2) Consignee :
A8: SHINTS BVT CO.,LTD VAT:0800006025 | G8: 10) L/C issuing bank
A9: PHU TAO RESIDENTIAL AREA,THACH KHOI WARD
A10: HAI DUONG CITY,HAI DUONG PROVINCE - VIETNAM
A11: TEL:84-320-3861727 FAX:84-320-3861730 | G11: 11) Remarks:
A12: XNK-Thy Ha <thyha@shintsbvt.com>
A13: 3) Notify party : | I13: FREIGHT CHARGE : | J13: =1500/324106.53*J29 -> 0
A14: THE SAME AS ABOVE | I14: INSURANCE CHARGE : | J14: =J29*1.1*0.026% -> 0
A16: 4) Port of loading: | D16: 5) Final Destination: | H16: C/T : | I16: 0 | J16: CT
H17: NET : | I17: =K29 -> 0 | J17: KGS
A18: INCHEON, KOREA | D18: HAIPHONG, VIETNAM | H18: GRS : | I18: =I17*1.1 -> 0 | J18: KGS
A19: 6) Carrier | D19: 7) Sailing on/ or About
A22: 12) Marks and Number of PKGS | D22: 13) Description of Goods | G22: 14) Quantity/Uint | I22: 15) Unit/price | J22: 16) Amount
G24: ( CIF HAIPHONG, VIETNAM )
D26: Desc | G26: Q'ty | H26: Unit | I26: Price | J26: Total
J27: =G27*I27 -> 0
J28: =G28*I28 -> 0
D29: TOTAL | J29: =SUM(J27:J28) -> 0 | K29: =SUM(K27:K28) -> 0
A30: DESC/SPEC | D30: HS CODE | F30: OFFER SPEC
A37: TEL NO. : 070-4006-3700~14, (DIR. 070-4006-3727)
A38: FAX NO. : (02)6330-2019 | H38: 17).Signed by :

Sheet V8
A1: COMMERCIAL INVOICE
A2: 1) Shipper/ Exporter : | G2: 8) No & Date of Invoice
A3: SHIN TEXTILE SOLUTIONS CO., LTD.
A4: 801, E&C VENTURE DREAMTOWER 2
A5: 55, DIGITAL-RO 33-GIL, GURO-GU, SEOUL, KOREA | G5: 9) No & Date L/C
A6: TEL : 070-4659-3337 FAX : 82-2-6330-2019
A7: 2) Consignee :
A8: SHINTS BVT CO.,LTD VAT:0800006025 | G8: 10) L/C issuing bank
A9: PHU TAO RESIDENTIAL AREA,THACH KHOI WARD
A10: HAI DUONG CITY,HAI DUONG PROVINCE - VIETNAM
A11: TEL:84-320-3861727 FAX:84-320-3861730 | G11: 11) Remarks:
A12: XNK-Thy Ha <thyha@shintsbvt.com>
A13: 3) Notify party : | I13: FREIGHT CHARGE : | J13: =1500/324106.53*J29 -> 0
A14: THE SAME AS ABOVE | I14: INSURANCE CHARGE : | J14: =J29*1.1*0.026% -> 0
A16: 4) Port of loading: | D16: 5) Final Destination: | H16: C/T : | I16: 0 | J16: CT
H17: NET : | I17: =K29 -> 0 | J17: KGS
A18: INCHEON, KOREA | D18: HAIPHONG, VIETNAM | H18: GRS : | I18: =I17*1.1 -> 0 | J18: KGS
A19: 6) Carrier | D19: 7) Sailing on/ or About
A22: 12) Marks and Number of PKGS | D22: 13) Description of Goods | G22: 14) Quantity/Uint | I22: 15) Unit/price | J22: 16) Amount
G24: ( CIF HAIPHONG, VIETNAM )
D26: Desc | G26: Q'ty | H26: Unit | I26: Price | J26: Total
J27: =G27*I27 -> 0
J28: =G28*I28 -> 0
D29: TOTAL | J29: =SUM(J27:J28) -> 0 | K29: =SUM(K27:K28) -> 0
A30: DESC/SPEC | D30: HS CODE | F30: OFFER SPEC
A37: TEL NO. : 070-4006-3700~14, (DIR. 070-4006-3727)
A38: FAX NO. : (02)6330-2019 | H38: 17).Signed by :

Sheet V9
A1: COMMERCIAL INVOICE
A2: 1) Shipper/ Exporter : | G2: 8) No & Date of Invoice
A3: SHIN TEXTILE SOLUTIONS CO., LTD.
A4: 801, E&C VENTURE DREAMTOWER 2
A5: 55, DIGITAL-RO 33-GIL, GURO-GU, SEOUL, KOREA | G5: 9) No & Date L/C
A6: TEL : 070-4659-3337 FAX : 82-2-6330-2019
A7: 2) Consignee :
A8: SHINTS BVT CO.,LTD VAT:0800006025 | G8: 10) L/C issuing bank
A9: PHU TAO RESIDENTIAL AREA,THACH KHOI WARD
A10: HAI DUONG CITY,HAI DUONG PROVINCE - VIETNAM
A11: TEL:84-320-3861727 FAX:84-320-3861730 | G11: 11) Remarks:
A12: XNK-Thy Ha <thyha@shintsbvt.com>
A13: 3) Notify party : | I13: FREIGHT CHARGE : | J13: =1500/324106.53*J29 -> 0
A14: THE SAME AS ABOVE | I14: INSURANCE CHARGE : | J14: =J29*1.1*0.026% -> 0
A16: 4) Port of loading: | D16: 5) Final Destination: | H16: C/T : | I16: 0 | J16: CT
H17: NET : | I17: =K29 -> 0 | J17: KGS
A18: INCHEON, KOREA | D18: HAIPHONG, VIETNAM | H18: GRS : | I18: =I17*1.1 -> 0 | J18: KGS
A19: 6) Carrier | D19: 7) Sailing on/ or About
A22: 12) Marks and Number of PKGS | D22: 13) Description of Goods | G22: 14) Quantity/Uint | I22: 15) Unit/price | J22: 16) Amount
G24: ( CIF HAIPHONG, VIETNAM )
D26: Desc | G26: Q'ty | H26: Unit | I26: Price | J26: Total
J27: =G27*I27 -> 0
J28: =G28*I28 -> 0
D29: TOTAL | J29: =SUM(J27:J28) -> 0 | K29: =SUM(K27:K28) -> 0
A30: DESC/SPEC | D30: HS CODE | F30: OFFER SPEC
A37: TEL NO. : 070-4006-3700~14, (DIR. 070-4006-3727)
A38: FAX NO. : (02)6330-2019 | H38: 17).Signed by :

Sheet V10
A1: COMMERCIAL INVOICE
A2: 1) Shipper/ Exporter : | G2: 8) No & Date of Invoice
A3: SHIN TEXTILE SOLUTIONS CO., LTD.
A4: 801, E&C VENTURE DREAMTOWER 2
A5: 55, DIGITAL-RO 33-GIL, GURO-GU, SEOUL, KOREA | G5: 9) No & Date L/C
A6: TEL : 070-4659-3337 FAX : 82-2-6330-2019
A7: 2) Consignee :
A8: SHINTS BVT CO.,LTD VAT:0800006025 | G8: 10) L/C issuing bank
A9: PHU TAO RESIDENTIAL AREA,THACH KHOI WARD
A10: HAI DUONG CITY,HAI DUONG PROVINCE - VIETNAM
A11: TEL:84-320-3861727 FAX:84-320-3861730 | G11: 11) Remarks:
A12: XNK-Thy Ha <thyha@shintsbvt.com>
A13: 3) Notify party : | I13: FREIGHT CHARGE : | J13: =1500/324106.53*J29 -> 0
A14: THE SAME AS ABOVE | I14: INSURANCE CHARGE : | J14: =J29*1.1*0.026% -> 0
A16: 4) Port of loading: | D16: 5) Final Destination: | H16: C/T : | I16: 0 | J16: CT
H17: NET : | I17: =K29 -> 0 | J17: KGS
A18: INCHEON, KOREA | D18: HAIPHONG, VIETNAM | H18: GRS : | I18: =I17*1.1 -> 0 | J18: KGS
A19: 6) Carrier | D19: 7) Sailing on/ or About
A22: 12) Marks and Number of PKGS | D22: 13) Description of Goods | G22: 14) Quantity/Uint | I22: 15) Unit/price | J22: 16) Amount
G24: ( CIF HAIPHONG, VIETNAM )
D26: Desc | G26: Q'ty | H26: Unit | I26: Price | J26: Total
J27: =G27*I27 -> 0
J28: =G28*I28 -> 0
D29: TOTAL | J29: =SUM(J27:J28) -> 0 | K29: =SUM(K27:K28) -> 0
A30: DESC/SPEC | D30: HS CODE | F30: OFFER SPEC
A37: TEL NO. : 070-4006-3700~14, (DIR. 070-4006-3727)
A38: FAX NO. : (02)6330-2019 | H38: 17).Signed by :

Sheet P
A1: DETAIL PACKING LIST FOR
A3: Supplier | B3: DESCRIPTION | C3: COLOR | D3: SPEC | E3: UNIT | F3: IN-Q'TY | G3: C/T Q'ty | H3: C/T No. | I3: Remark
A7: TOTAL | B7: BALES | F7: =SUM(F4:F6) -> 0 | G7: =SUM(G4:G6) -> 0

Sheet C.INV
A1: COMMERCIAL INVOICE
A2: 1) Shipper/ Exporter : | G2: 8) No & Date of Invoice
A3: SHIN TEXTILE SOLUTIONS CO., LTD.
A4: 801, E&C VENTURE DREAMTOWER 2
A5: 55, DIGITAL-RO 33-GIL, GURO-GU, SEOUL, KOREA | G5: 9) No & Date L/C
A6: TEL : 070-4659-3337 FAX : 82-2-6330-2019
A7: 2) Consignee :
A8: SHINTS BVT CO.,LTD VAT:0800006025 | G8: 10) L/C issuing bank
A9: PHU TAO RESIDENTIAL AREA,THACH KHOI WARD
A10: HAI DUONG CITY,HAI DUONG PROVINCE - VIETNAM
A11: TEL:84-320-3861727 FAX:84-320-3861730 | G11: 11) Remarks:
A12: XNK-Thy Ha <thyha@shintsbvt.com>
A13: 3) Notify party :
A14: THE SAME AS ABOVE
A16: 4) Port of loading: | D16: 5) Final Destination:
A18: INCHEON, KOREA | D18: HAIPHONG, VIETNAM
A19: 6) Carrier | D19: 7) Sailing on/ or About
A22: 12) Marks and Number of PKGS | D22: 13) Description of Goods | G22: 14) Quantity/Uint | I22: 15) Unit/price | J22: 16) Amount
G24: ( CIF HAIPHONG, VIETNAM )
A25: SHINTS BVT
A26: (IN DIA)
D27: MATERIALS FOR GARMENT
A28: STYLE NO.:
A29: ITEM :
A30: Q'TY :
A31: C/T NO. : | D31: TOTAL | J31: =+D.INV!G12 -> 0
J32: =SUM(#REF!,#REF!,#REF!,#REF!,#REF!,#REF!,#REF!,#REF!,#REF!,#REF!,#REF!) -> #REF!
A40: TEL NO. : 070-4006-3700~14, (DIR. 070-4006-3727)
A41: FAX NO. : (02)6330-2019 | H41: 17).Signed by :

Sheet BVT.INV
A1: PROFORMA INVOICE FOR BVT
A3: No | B3: HS_No | C3: Matl Name | D3: Unit Price | E3: Q'ty | F3: Unit | G3: Amount | H3: Country | I3: Weight | K3: Width | L3: Composition
J4: kg
J5: kg
B6: GRAND TOTAL : | E6: =SUM(E4:E5) -> 0 | G6: =SUM(G4:G5) -> 0 | I6: =SUM(I4:I5) -> 0 | J6: kg

Sheet D.INV
A1: DETAILS FOR
A3: No. | B3: ORDER No. | C3: STYLE | D3: QUANTITY | E3: UNIT | F3: DELIVERY
A8: No | B8: HS_No | C8: HS Name | D8: Unit Price | E8: Q'ty | F8: Unit | G8: Amount | H8: Country | I8: Weight
G9: 0 | J9: g
G10: 0 | J10: g
G11: 0 | J11: g
B12: GRAND TOTAL : | E12: =SUM(E9:E11) -> 0 | G12: =SUM(G9:G11) -> 0
E14: G.TOTAL | G14: =SC!J29 -> 0

Sheet PAC
A1: PACKING LIST
A2: 1) Shipper/ Exporter: | G2: 8) No & Date of Invoice
A3: SHIN TEXTILE SOLUTIONS CO., LTD.
A4: 801, E&C VENTURE DREAMTOWER 2
A5: 55, DIGITAL-RO 33-GIL, GURO-GU, SEOUL, KOREA | G5: 9) Remarks:
A6: TEL : 070-4659-3337 FAX : 82-2-6330-2019
A7: 2) Consignee :
A8: SHINTS BVT CO.,LTD VAT:0800006025
A9: PHU TAO RESIDENTIAL AREA,THACH KHOI WARD
A10: HAI DUONG CITY,HAI DUONG PROVINCE - VIETNAM
A11: TEL:84-320-3861727 FAX:84-320-3861730
A12: XNK-Thy Ha <thyha@shintsbvt.com>
A13: 3) Notify party :
A14: THE SAME AS ABOVE
A16: 4) Port of loading: | D16: 5) Final Destination:
A18: INCHEON, KOREA | D18: HAIPHONG, VIETNAM
A19: 6) Carrier | D19: 7) Sailing on/ or About
A22: 10) Marks and Number of PKGS | D22: 11) Description of Goods | G22: 12) Quantity | I22: 13) Net | J22: 14) Gross | K22: 15) Measurement
I23: Weight | J23: Weight
D25: TOTAL : | G25: =VLOOKUP("TOTAL",P!A:I,7,0) -> 0 | I25: =BVT.INV!I6 -> 0 | J25: =I25*1.1 -> 0 | K25: =J25/166 -> 0
A27: SHINTS BVT
A28: (IN DIA)
D29: MATERIALS FOR GARMENT
A30: STYLE NO.:
A31: ITEM :
A32: Q'TY :
A33: C/T NO. : | D33: TOTAL
A51: TEL NO. : (02)6330-2000~14, (DIR. 6330-2012)
A52: FAX NO. : (02)6330-2019 | H52: 16).Signed by :

Sheet D.PAC
A1: DETAIL PACKING LIST FOR
A3: Supplier | B3: MATL CODE | C3: DESCRIPTION | D3: COLOR | E3: SPEC | F3: UNIT | G3: IN-Q'TY | H3: C/T Q'ty | I3: C/T No. | J3: Remark
A7: TOTAL | C7: BALES | G7: =SUM(G4:G6) -> 0 | H7: =SUM(H4:H6) -> 0

Sheet SC
A1: SALES CONTRACT
A2: 1) Seller : | G2: 8) No & Date of Invoice
A3: SHIN TEXTILE SOLUTIONS CO., LTD.
A4: 801, E&C VENTURE DREAMTOWER 2, 55, | G4: stb | K4: 42872
A5: DIGITAL-RO,33-GIL,GURO-GU,SEOUL,KOREA
A6: TEL : 82-2-6330-2000 FAX : 82-2-6330-2019
A7: 2) Buyer : | G7: 9) Remarks:
A8: SHINTS BVT CO.,LTD VAT:0800006025
A9: PHU TAO RESIDENTIAL AREA,THACH KHOI WARD
A10: HAI DUONG CITY,HAI DUONG PROVINCE - VIETNAM
A11: TEL:84-320-3861727 FAX:84-320-3861730
A12: XNK-Thy Ha <thyha@shintsbvt.com>
A13: 3) Price term :
A14: CFR
A16: 4) Port of loading : | D16: 5) Final Destination :
A18: INCHEON, KOREA | D18: VIETNAM ANY PORT
A19: 6) Shipmode : | D19: 7) Shipping Date :
A21: SEA OR AIR
D22: 10) Description of Goods | G22: 11) Quantity/Uint | I22: 12) Unit/price | J22: 13) Amount
D27: MATERIALS FOR GARMENT
D28: DETAIL - ATTACHED FILE
D29: TOTAL
D32: 1) Price term : | G32: CFR
D33: 2) Destination: | G33: VIETNAM
D34: 3) Consignee & | G34: SHINTS BVT CO.,LTD.
D35: Notify | G35: THACH KHOI WARD, HAI DUONG CITY,
G36: HAI DUONG PROVINCE, VIET NAM
D37: 4) Loading port : | G37: KOREA PORT
D38: 5) Insurance :
D39: 6) Packing | G39: STANDARD PACKING
D40: 7) Payment by | G40: PREPAID PAYMENT BEFORE SHIPMENT
D41: 8) Bank Details
D43: Bank Name | F43: WOORI BANK, GURO DIGITAL VALLEY BRANCH
D44: Bank Address | F44: 1F, 182-13, GURO-DONG, GURO-GU, SEOUL, KOREA
D45: Account Name | F45: SHIN TEXTILE SOLUTIONS CO.,LTD.
D46: Account No. | F46: 1081-400-467685
D47: Swift Code | F47: HVBKKRSEXXX
A56: 14).Signed by : | H56: 15).Signed by :
B57: Mr. Ha Dong Wan | I57: Mrs. Shin
B58: SHINTS BVT CO.,LTD. | I58: SHIN TEXTILE SOLUTIONS CO., LTD.

Sheet PIM
A1: ATTACH OF SALES CONTRACT NO.
A3: No. | B3: ORDER No. | C3: STYLE | D3: QUANTITY | E3: UNIT | F3: DELIVERY
A8: No | B8: HS_No | C8: HS Name | D8: Unit Price | E8: Q'ty | F8: Unit | G8: Amount | H8: Country | I8: Weight
G9: 0 | J9: g
G10: 0 | J10: g
G11: 0 | J11: g
B12: GRAND TOTAL : | E12: =SUM(E9:E11) -> 0 | G12: =SUM(G9:G11) -> 0
E14: G.TOTAL | G14: =SC!J29 -> 0

Sheet Sheet1
